{"result": {"totalResults": 41, "data": [{"address": {"city": "BOSTON", "formatted": "271 Dartmouth St BOSTON, MA 02116", "postal_code": "02116", "state": "MA", "street": "271 Dartmouth St"}, "cuisines": ["Mexican", "Nuevo Latino"], "geo": {"lat": 42.350652, "lon": -71.077398}, "item_id": 84612398, "menu_item_description": "Sesame baguette, cotija cheese candied cumin and chili flakes.", "menu_item_name": "Avocado Toast", "menu_item_pricing": [{"currency": "USD", "price": 9, "priceString": "$9.00"}], "price_range": "$", "restaurant_hours": "Daily: 5pm-2am", "restaurant_id": 353440, "restaurant_name": "Lolita", "restaurant_phone": "(617) 369-5609", "subsection": "Snacks", "subsection_description": " "}, {"address": {"city": "BOSTON", "formatted": "271 Dartmouth St BOSTON, MA 02116", "postal_code": "02116", "state": "MA", "street": "271 Dartmouth St"}, "cuisines": ["Mexican", "Nuevo Latino"], "geo": {"lat": 42.350652, "lon": -71.077398}, "item_id": 84614278, "menu_item_description": "Kimchee mayo, pickled shishito peppers and japanese peanuts.", "menu_item_name": "Fried Chicken Taco", "menu_item_pricing": [{"currency": "USD", "price": 11, "priceString": "$11.00"}], "price_range": "$", "restaurant_hours": "Daily: 5pm-2am", "restaurant_id": 353440, "restaurant_name": "Lolita", "restaurant_phone": "(617) 369-5609", "subsection": "Tacos", "subsection_description": " "}, {"address": {"city": "BOSTON", "formatted": "271 Dartmouth St BOSTON, MA 02116", "postal_code": "02116", "state": "MA", "street": "271 Dartmouth St"}, "cuisines": ["Mexican", "Nuevo Latino"], "geo": {"lat": 42.350652, "lon": -71.077398}, "item_id": 84614638, "menu_item_description": "Tomato, roasted serrano, red onion, cilantro and lime.", "menu_item_name": "Fresco", "menu_item_pricing": [{"currency": "USD", "price": 10, "priceString": "$10.00"}], "price_range": "$", "restaurant_hours": "Daily: 5pm-2am", "restaurant_id": 353440, "restaurant_name": "Lolita", "restaurant_phone": "(617) 369-5609", "subsection": "Guacamole", "subsection_description": " "}, {"address": {"city": "BOSTON", "formatted": "271 Dartmouth St BOSTON, MA 02116", "postal_code": "02116", "state": "MA", "street": "271 Dartmouth St"}, "cuisines": ["Mexican", "Nuevo Latino"], "geo": {"lat": 42.350652, "lon": -71.077398}, "item_id": 84614758, "menu_item_description": "Smokey applewood bacon, adobo diced tomato and cilantro.", "menu_item_name": "Tocino", "menu_item_pricing": [{"currency": "USD", "price": 12, "priceString": "$12.00"}], "price_range": "$", "restaurant_hours": "Daily: 5pm-2am", "restaurant_id": 353440, "restaurant_name": "Lolita", "restaurant_phone": "(617) 369-5609", "subsection": "Guacamole", "subsection_description": " "}, {"address": {"city": "BOSTON", "formatted": "271 Dartmouth St BOSTON, MA 02116", "postal_code": "02116", "state": "MA", "street": "271 Dartmouth St"}, "cuisines": ["Mexican", "Nuevo Latino"], "geo": {"lat": 42.350652, "lon": -71.077398}, "item_id": 84614998, "menu_item_description": "Warm cinnamon sugared mexican donuts made to order sweet milk almond sauce and hot fudge for dipping.", "menu_item_name": "Churros", "menu_item_pricing": [{"currency": "USD", "price": 10, "priceString": "$10.00"}], "price_range": "$", "restaurant_hours": "Daily: 5pm-2am", "restaurant_id": 353440, "restaurant_name": "Lolita", "restaurant_phone": "(617) 369-5609", "subsection": "Finishing Touches", "subsection_description": " "}, {"address": {"city": "BOSTON", "formatted": "271 Dartmouth St BOSTON, MA 02116", "postal_code": "02116", "state": "MA", "street": "271 Dartmouth St"}, "cuisines": ["Mexican", "Nuevo Latino"], "geo": {"lat": 42.350652, "lon": -71.077398}, "item_id": 84615303, "menu_item_description": "Stolitchnaya vanilla vodka, coconut puree, fresh shaken cream and fresh squeezed lime.", "menu_item_name": "Key Lime Kiss", "menu_item_pricing": [{"currency": "USD", "price": 10, "priceString": "$10.00"}], "price_range": "$", "restaurant_hours": "Daily: 5pm-2am", "restaurant_id": 353440, "restaurant_name": "Lolita", "restaurant_phone": "(617) 369-5609", "subsection": "Tequila Night Caps", "subsection_description": " "}, {"address": {"city": "BOSTON", "formatted": "271 Dartmouth St BOSTON, MA 02116", "postal_code": "02116", "state": "MA", "street": "271 Dartmouth St"}, "cuisines": ["Mexican", "Nuevo Latino"], "geo": {"lat": 42.350652, "lon": -71.077398}, "item_id": 84612458, "menu_item_description": "Jalapeno mayo, cotija cheese and chile lime powder.", "menu_item_name": "Grilled Street Corn", "menu_item_pricing": [{"currency": "USD", "price": 9, "priceString": "$9.00"}], "price_range": "$", "restaurant_hours": "Daily: 5pm-2am", "restaurant_id": 353440, "restaurant_name": "Lolita", "restaurant_phone": "(617) 369-5609", "subsection": "Snacks", "subsection_description": " "}, {"address": {"city": "BOSTON", "formatted": "271 Dartmouth St BOSTON, MA 02116", "postal_code": "02116", "state": "MA", "street": "271 Dartmouth St"}, "cuisines": ["Mexican", "Nuevo Latino"], "geo": {"lat": 42.350652, "lon": -71.077398}, "item_id": 84613528, "menu_item_description": "Romaine, cabbage, cucumber, corn, roasted peppers, manchego, chile lime ranch.", "menu_item_name": "Jicama Chopped Salad", "menu_item_pricing": [{"currency": "USD", "price": 11, "priceString": "$11.00"}], "price_range": "$", "restaurant_hours": "Daily: 5pm-2am", "restaurant_id": 353440, "restaurant_name": "Lolita", "restaurant_phone": "(617) 369-5609", "subsection": "Street Food", "subsection_description": " "}, {"address": {"city": "BOSTON", "formatted": "271 Dartmouth St BOSTON, MA 02116", "postal_code": "02116", "state": "MA", "street": "271 Dartmouth St"}, "cuisines": ["Mexican", "Nuevo Latino"], "geo": {"lat": 42.350652, "lon": -71.077398}, "item_id": 84614698, "menu_item_description": "Jumbo lump crab, maine lobster garlic herb butter.", "menu_item_name": "Especial", "menu_item_pricing": [{"currency": "USD", "price": 15, "priceString": "$15.00"}], "price_range": "$", "restaurant_hours": "Daily: 5pm-2am", "restaurant_id": 353440, "restaurant_name": "Lolita", "restaurant_phone": "(617) 369-5609", "subsection": "Guacamole", "subsection_description": " "}, {"address": {"city": "BOSTON", "formatted": "271 Dartmouth St BOSTON, MA 02116", "postal_code": "02116", "state": "MA", "street": "271 Dartmouth St"}, "cuisines": ["Mexican", "Nuevo Latino"], "geo": {"lat": 42.350652, "lon": -71.077398}, "item_id": 84612878, "menu_item_description": "Deep pepper marinade, salsa verde cucumber cream and crunchy quinoa.", "menu_item_name": "Chicken Asado Skewers", "menu_item_pricing": [{"currency": "USD", "price": 11, "priceString": "$11.00"}], "price_range": "$", "restaurant_hours": "Daily: 5pm-2am", "restaurant_id": 353440, "restaurant_name": "Lolita", "restaurant_phone": "(617) 369-5609", "subsection": "Street Food", "subsection_description": " "}], "numResults": 10, "page": 1, "pages": 2, "morePages": true}}